README.md
setup.py
x735/__init__.py
x735/config.py
x735/fan.py
x735/main.py
x735_v2.5.egg-info/PKG-INFO
x735_v2.5.egg-info/SOURCES.txt
x735_v2.5.egg-info/dependency_links.txt
x735_v2.5.egg-info/entry_points.txt
x735_v2.5.egg-info/requires.txt
x735_v2.5.egg-info/top_level.txt