Metadata-Version: 2.1
Name: x735-v2.5
Version: 0.3.1
Summary: Library for board x735
Home-page: https://github.com/shitikovkirill/x735-v2.5
Author: sh.kiruh@gmail.com
License: UNKNOWN
Download-URL: https://github.com/shitikovkirill/x735-v2.5/archive/refs/heads/main.zip
Platform: UNKNOWN
Requires-Python: >=3.7
Provides-Extra: dev
